yomitoku/__init__.py
yomitoku/base.py
yomitoku/constants.py
yomitoku/document_analyzer.py
yomitoku/layout_analyzer.py
yomitoku/layout_parser.py
yomitoku/ocr.py
yomitoku/reading_order.py
yomitoku/schemas.py
yomitoku/table_structure_recognizer.py
yomitoku/text_detector.py
yomitoku/text_recognizer.py
yomitoku/cli/__init__.py
yomitoku/cli/download_model.py
yomitoku/cli/main.py
yomitoku/cli/mcp_server.py
yomitoku/configs/__init__.py
yomitoku/configs/cfg_layout_parser_rtdtrv2.py
yomitoku/configs/cfg_layout_parser_rtdtrv2_v2.py
yomitoku/configs/cfg_table_structure_recognizer_rtdtrv2.py
yomitoku/configs/cfg_text_detector_dbnet.py
yomitoku/configs/cfg_text_detector_dbnet_v2.py
yomitoku/configs/cfg_text_recognizer_parseq.py
yomitoku/configs/cfg_text_recognizer_parseq_small.py
yomitoku/configs/cfg_text_recognizer_parseq_tiny.py
yomitoku/configs/cfg_text_recognizer_parseq_v2.py
yomitoku/data/__init__.py
yomitoku/data/dataset.py
yomitoku/data/functions.py
yomitoku/export/__init__.py
yomitoku/export/export_csv.py
yomitoku/export/export_html.py
yomitoku/export/export_json.py
yomitoku/export/export_markdown.py
yomitoku/models/__init__.py
yomitoku/models/dbnet_plus.py
yomitoku/models/parseq.py
yomitoku/models/rtdetr.py
yomitoku/models/layers/__init__.py
yomitoku/models/layers/activate.py
yomitoku/models/layers/dbnet_feature_attention.py
yomitoku/models/layers/parseq_transformer.py
yomitoku/models/layers/rtdetr_backbone.py
yomitoku/models/layers/rtdetr_hybrid_encoder.py
yomitoku/models/layers/rtdetrv2_decoder.py
yomitoku/onnx/.gitkeep
yomitoku/postprocessor/__init__.py
yomitoku/postprocessor/dbnet_postporcessor.py
yomitoku/postprocessor/parseq_tokenizer.py
yomitoku/postprocessor/rtdetr_postprocessor.py
yomitoku/resource/MPLUS1p-Medium.ttf
yomitoku/resource/ShipporiMinchoB1-Bold.ttf
yomitoku/resource/charset.txt
yomitoku/resource/charsetv2.txt
yomitoku/utils/__init__.py
yomitoku/utils/graph.py
yomitoku/utils/logger.py
yomitoku/utils/misc.py
yomitoku/utils/searchable_pdf.py
yomitoku-0.10.1.dist-info/METADATA
yomitoku-0.10.1.dist-info/WHEEL
yomitoku-0.10.1.dist-info/entry_points.txt
yomitoku-0.10.1.dist-info/RECORD
