Metadata-Version: 2.4
Name: yomitoku
Version: 0.10.1
Summary: Yomitoku is an AI-powered document image analysis package designed specifically for the Japanese language.
Author-email: Kotaro Kinoshita <kotaro.kinoshita@mlism.com>
License: CC BY-NC-SA 4.0
Keywords: Deep Learning,Japanese,OCR
Requires-Python: <3.13,>=3.10
Requires-Dist: huggingface-hub>=0.26.1
Requires-Dist: jaconv>=0.4.0
Requires-Dist: lxml>=5.3.0
Requires-Dist: omegaconf>=2.3.0
Requires-Dist: onnx>=1.17.0
Requires-Dist: onnxruntime>=1.20.1
Requires-Dist: onnxscript>=0.5.4
Requires-Dist: opencv-python>=4.10.0.84
Requires-Dist: pyclipper>=1.3.0.post6
Requires-Dist: pydantic>=2.9.2
Requires-Dist: pypdfium2==4.30.0
Requires-Dist: reportlab>=4.4.1
Requires-Dist: shapely>=2.0.6
Requires-Dist: timm>=1.0.11
Requires-Dist: torch>=2.5.0
Requires-Dist: torchvision>=0.20.0
Provides-Extra: mcp
Requires-Dist: mcp[cli]>=1.6.0; extra == 'mcp'
